Metadata-Version: 1.0
Name: CC-distributions
Version: 0.1
Summary: Gaussian * Binomial distributions
Home-page: UNKNOWN
Author: Cooper Chastain
Author-email: UNKNOWN
License: UNKNOWN
Platform: UNKNOWN
